aiida_calcmonitor/__init__.py
aiida_calcmonitor/calculations/__init__.py
aiida_calcmonitor/calculations/calcjob_monitor.py
aiida_calcmonitor/calculations/toymodel_calcjob.py
aiida_calcmonitor/cli/__init__.py
aiida_calcmonitor/cli/root.py
aiida_calcmonitor/data/monitors/__init__.py
aiida_calcmonitor/data/monitors/monitor_base.py
aiida_calcmonitor/data/monitors/monitor_tomato.py
aiida_calcmonitor/data/monitors/monitor_toymodel.py
aiida_calcmonitor/parsers/monitor_tomato.py
aiida_calcmonitor/utils/__init__.py
aiida_calcmonitor/utils/calcjob_monitor.py
aiida_calcmonitor/utils/helpers.py
aiida_calcmonitor/utils/toymodel_code.sh
aiida_calcmonitor/workflows/monitor_wrapper.py
aiida_calcmonitor/workflows/monitored_cycler.py
aiida_calcmonitor-0.1.0.dist-info/entry_points.txt
aiida_calcmonitor-0.1.0.dist-info/LICENSE
aiida_calcmonitor-0.1.0.dist-info/WHEEL
aiida_calcmonitor-0.1.0.dist-info/METADATA
aiida_calcmonitor-0.1.0.dist-info/RECORD
